multi/__init__.py
multi/__main__.py
multi/_version.py
multi/cli.py
multi/cli_helpers.py
multi/errors.py
multi/git_helpers.py
multi/git_run.py
multi/git_set_branch.py
multi/ignore_files.py
multi/init.py
multi/logging.py
multi/paths.py
multi/repos.py
multi/rules.py
multi/settings.py
multi/sync.py
multi/sync_claude.py
multi/sync_ruff.py
multi/sync_vscode.py
multi/sync_vscode_extensions.py
multi/sync_vscode_helpers.py
multi/sync_vscode_launch.py
multi/sync_vscode_settings.py
multi/sync_vscode_tasks.py
multi/utils.py
multi/resources/init_readme.md
multi_workspace-3.0.5.dist-info/METADATA
multi_workspace-3.0.5.dist-info/WHEEL
multi_workspace-3.0.5.dist-info/entry_points.txt
multi_workspace-3.0.5.dist-info/licenses/LICENSE
multi_workspace-3.0.5.dist-info/RECORD
