Metadata-Version: 2.4
Name: multi-workspace
Version: 3.0.5
Summary: Multi
Project-URL: Repository, https://github.com/gabemontague/multi
Project-URL: Issues, https://github.com/gabemontague/multi/issues
Author-email: Gabe Montague <gabemontague@outlook.com>
License-File: LICENSE
Classifier: Environment :: Console
Classifier: Intended Audience :: Developers
Classifier: License :: OSI Approved :: MIT License
Classifier: Operating System :: OS Independent
Classifier: Programming Language :: Python :: 3
Classifier: Topic :: Software Development :: Version Control :: Git
Requires-Python: >=3.9
Requires-Dist: click>=8.3.1
Requires-Dist: gitpython>=3.1.0
Provides-Extra: dev
Requires-Dist: pyinstaller>=6.9.0; extra == 'dev'
Requires-Dist: pytest-cov>=6.1.1; extra == 'dev'
Requires-Dist: pytest-mock>=3.14.0; extra == 'dev'
Requires-Dist: pytest>=8.3.5; extra == 'dev'
Requires-Dist: ruff>=0.11.10; extra == 'dev'
